{
    "4.000000": {
        "0.275000": {
            "0.375000": {
                "error_ratio": 1.0381613139139076,
                "value_ratio": 4.91852296244815
            },
            "0.425000": {
                "error_ratio": 1.175425049436419,
                "value_ratio": 5.640604589039153
            },
            "0.475000": {
                "error_ratio": 0.7737148183053929,
                "value_ratio": 2.7303493321873833
            },
            "0.525000": {
                "error_ratio": 0.5600538532442861,
                "value_ratio": 2.5419409625285185
            },
            "0.575000": {
                "error_ratio": 0.5602450478449629,
                "value_ratio": 3.0702738889574896
            },
            "0.625000": {
                "error_ratio": 0.5540803226099419,
                "value_ratio": 3.6578292152404326
            },
            "0.675000": {
                "error_ratio": 0.3362578609446416,
                "value_ratio": 2.012706362514037
            },
            "0.725000": {
                "error_ratio": 0.45430623253766983,
                "value_ratio": 2.0516685530374676
            },
            "0.775000": {
                "error_ratio": 0.5450835954790555,
                "value_ratio": 1.9367177576305012
            }
        },
        "0.325000": {
            "0.325000": {
                "error_ratio": 2.5941474622603993,
                "value_ratio": 5.2543572141026536
            },
            "0.375000": {
                "error_ratio": 0.814456613004592,
                "value_ratio": 5.967685616364281
            },
            "0.425000": {
                "error_ratio": 0.40606353602235323,
                "value_ratio": 4.5799051878273245
            },
            "0.475000": {
                "error_ratio": 0.45534778262720926,
                "value_ratio": 5.047283594699161
            },
            "0.525000": {
                "error_ratio": 0.3737208276119199,
                "value_ratio": 4.491500411892049
            },
            "0.575000": {
                "error_ratio": 0.32245175926563724,
                "value_ratio": 3.907777700010519
            },
            "0.625000": {
                "error_ratio": 0.240191797053542,
                "value_ratio": 2.9609950340775293
            },
            "0.675000": {
                "error_ratio": 0.18421975800490467,
                "value_ratio": 2.421771324226589
            },
            "0.725000": {
                "error_ratio": 0.23877156446590236,
                "value_ratio": 2.2640380142960628
            },
            "0.775000": {
                "error_ratio": 0.5417017078433523,
                "value_ratio": 2.1277487499273002
            }
        },
        "0.375000": {
            "0.325000": {
                "error_ratio": 1.090969853140913,
                "value_ratio": 4.689794711248315
            },
            "0.375000": {
                "error_ratio": 0.479251987640374,
                "value_ratio": 5.035916784800799
            },
            "0.425000": {
                "error_ratio": 0.3533623447230559,
                "value_ratio": 4.397166541251393
            },
            "0.475000": {
                "error_ratio": 0.29634115077530176,
                "value_ratio": 4.238070726212518
            },
            "0.525000": {
                "error_ratio": 0.31967313449294105,
                "value_ratio": 4.433593607560051
            },
            "0.575000": {
                "error_ratio": 0.2907459551711885,
                "value_ratio": 4.071596446363426
            },
            "0.625000": {
                "error_ratio": 0.20385807383304524,
                "value_ratio": 2.983225130056571
            },
            "0.675000": {
                "error_ratio": 0.20869729375112253,
                "value_ratio": 2.7927403041114855
            },
            "0.725000": {
                "error_ratio": 0.45629763387524724,
                "value_ratio": 3.405784170236725
            }
        },
        "0.425000": {
            "0.325000": {
                "error_ratio": 1.9960870219983016,
                "value_ratio": 7.205815566946296
            },
            "0.375000": {
                "error_ratio": 0.5062405290186913,
                "value_ratio": 4.870626769987317
            },
            "0.425000": {
                "error_ratio": 0.4387063035339877,
                "value_ratio": 4.99413688715057
            },
            "0.475000": {
                "error_ratio": 0.3067809959733198,
                "value_ratio": 4.1157856686896785
            },
            "0.525000": {
                "error_ratio": 0.2757354834249037,
                "value_ratio": 3.9066835540876608
            },
            "0.575000": {
                "error_ratio": 0.29072468771927124,
                "value_ratio": 3.9374060252841976
            },
            "0.625000": {
                "error_ratio": 0.2995975839730303,
                "value_ratio": 3.1265688712658575
            },
            "0.675000": {
                "error_ratio": 0.3598864341436354,
                "value_ratio": 2.498440663946623
            },
            "0.725000": {
                "error_ratio": 0.6273245458653652,
                "value_ratio": 1.2668940091972183
            }
        },
        "0.475000": {
            "0.375000": {
                "error_ratio": 0.798610900734905,
                "value_ratio": 5.923991895170656
            },
            "0.425000": {
                "error_ratio": 0.5527891422480069,
                "value_ratio": 5.131327444465971
            },
            "0.475000": {
                "error_ratio": 0.3431531943238771,
                "value_ratio": 3.659096565748938
            },
            "0.525000": {
                "error_ratio": 0.38793389361627545,
                "value_ratio": 3.8039376853833926
            },
            "0.575000": {
                "error_ratio": 0.5508159232919074,
                "value_ratio": 4.2370948893493745
            },
            "0.625000": {
                "error_ratio": 1.0305552541361964,
                "value_ratio": 2.6764743705745313
            }
        },
        "0.525000": {
            "0.375000": {
                "error_ratio": 1.51199588935902,
                "value_ratio": 6.852392320774931
            },
            "0.425000": {
                "error_ratio": 0.7481525507679958,
                "value_ratio": 4.488433382365289
            },
            "0.475000": {
                "error_ratio": 0.9158025724458214,
                "value_ratio": 5.236172235006755
            },
            "0.525000": {
                "error_ratio": 1.00583504192051,
                "value_ratio": 3.5752481155116858
            }
        },
        "0.575000": {
            "0.375000": {
                "error_ratio": 5.039658795760957,
                "value_ratio": 9.579863550595308
            },
            "0.425000": {
                "error_ratio": 1.049552115618454,
                "value_ratio": 3.4967565992810865
            }
        }
    },
    "4.750000": {
        "0.325000": {
            "0.475000": {
                "error_ratio": 2.063816999142158,
                "value_ratio": 4.006887904929584
            },
            "0.525000": {
                "error_ratio": 1.4950183846774536,
                "value_ratio": 2.8905381398645416
            },
            "0.675000": {
                "error_ratio": 0.8688830294120563,
                "value_ratio": 1.1197276220973795
            },
            "0.725000": {
                "error_ratio": 0.4715278035317434,
                "value_ratio": 0.3030977636909406
            }
        },
        "0.375000": {
            "0.375000": {
                "error_ratio": 0.5408470802485931,
                "value_ratio": 4.465409427743953
            },
            "0.425000": {
                "error_ratio": 0.41828241266830224,
                "value_ratio": 3.921956531384694
            },
            "0.475000": {
                "error_ratio": 0.3889701712901816,
                "value_ratio": 3.309885667545541
            },
            "0.525000": {
                "error_ratio": 0.48779102485890763,
                "value_ratio": 4.349390132382744
            },
            "0.575000": {
                "error_ratio": 0.5026725753025002,
                "value_ratio": 4.140053973290198
            },
            "0.625000": {
                "error_ratio": 0.31962885305039895,
                "value_ratio": 2.961440677856067
            },
            "0.675000": {
                "error_ratio": 0.31538524163762827,
                "value_ratio": 2.633368244089278
            },
            "0.725000": {
                "error_ratio": 0.8084934628212224,
                "value_ratio": 3.2546948645501406
            }
        },
        "0.425000": {
            "0.325000": {
                "error_ratio": 1.9152980589471817,
                "value_ratio": 6.306600227661072
            },
            "0.375000": {
                "error_ratio": 0.45620525986652183,
                "value_ratio": 5.383846284370111
            },
            "0.425000": {
                "error_ratio": 0.30318224058289234,
                "value_ratio": 4.263035004650643
            },
            "0.475000": {
                "error_ratio": 0.370118393354253,
                "value_ratio": 4.60740423554586
            },
            "0.525000": {
                "error_ratio": 0.2671522408412057,
                "value_ratio": 3.9562063288082117
            },
            "0.575000": {
                "error_ratio": 0.24672252985983303,
                "value_ratio": 3.5756854698289295
            },
            "0.625000": {
                "error_ratio": 0.23574778802001653,
                "value_ratio": 3.116636675660081
            },
            "0.675000": {
                "error_ratio": 0.23699403071483532,
                "value_ratio": 2.5810090802058907
            }
        },
        "0.475000": {
            "0.325000": {
                "error_ratio": 1.9010556037969253,
                "value_ratio": 6.728411699517515
            },
            "0.375000": {
                "error_ratio": 0.4210264766105169,
                "value_ratio": 5.114423719729478
            },
            "0.425000": {
                "error_ratio": 0.3377879903039024,
                "value_ratio": 4.820296964266068
            },
            "0.475000": {
                "error_ratio": 0.2593119184588943,
                "value_ratio": 3.9256050882734086
            },
            "0.525000": {
                "error_ratio": 0.25154877537104736,
                "value_ratio": 4.098641513161413
            },
            "0.575000": {
                "error_ratio": 0.24178967680630983,
                "value_ratio": 3.6783338963428718
            },
            "0.625000": {
                "error_ratio": 0.2380701492551922,
                "value_ratio": 2.842910245949514
            },
            "0.675000": {
                "error_ratio": 0.5439866620991409,
                "value_ratio": 1.5429288913815387
            }
        },
        "0.525000": {
            "0.325000": {
                "error_ratio": 2.8865035321264796,
                "value_ratio": 6.358981506016121
            },
            "0.375000": {
                "error_ratio": 0.504994994256261,
                "value_ratio": 5.318020435675089
            },
            "0.425000": {
                "error_ratio": 0.43244728698255025,
                "value_ratio": 5.382415488591829
            },
            "0.475000": {
                "error_ratio": 0.29862766412577235,
                "value_ratio": 3.6750742772213876
            },
            "0.525000": {
                "error_ratio": 0.36619501877713084,
                "value_ratio": 3.8596134692298913
            },
            "0.575000": {
                "error_ratio": 0.4063773715959617,
                "value_ratio": 3.74079646707667
            },
            "0.625000": {
                "error_ratio": 1.3908256453341388,
                "value_ratio": 3.9815846455996318
            }
        },
        "0.575000": {
            "0.375000": {
                "error_ratio": 0.8825429271190469,
                "value_ratio": 5.256956967842414
            },
            "0.425000": {
                "error_ratio": 1.107425071857703,
                "value_ratio": 6.132652889479355
            },
            "0.475000": {
                "error_ratio": 0.5922971523578241,
                "value_ratio": 4.180386925971769
            },
            "0.525000": {
                "error_ratio": 0.8489560747893466,
                "value_ratio": 3.1253229818179187
            }
        },
        "0.625000": {
            "0.375000": {
                "error_ratio": 1.2788811405528433,
                "value_ratio": 3.2319129646878144
            }
        }
    },
    "5.500000": {
        "0.375000": {
            "0.375000": {
                "error_ratio": 1.3875306267896026,
                "value_ratio": 2.696530747178713
            },
            "0.425000": {
                "error_ratio": 1.0940494378867074,
                "value_ratio": 2.0354173465919994
            },
            "0.525000": {
                "error_ratio": 1.4827200284564566,
                "value_ratio": 3.475650014903045
            },
            "0.575000": {
                "error_ratio": 0.9256644334803151,
                "value_ratio": 2.6549687059598166
            },
            "0.625000": {
                "error_ratio": 0.5986529595899645,
                "value_ratio": 1.7142975294268585
            },
            "0.675000": {
                "error_ratio": 0.43376612365977574,
                "value_ratio": 1.0290977638940293
            }
        },
        "0.425000": {
            "0.325000": {
                "error_ratio": 1.1272215427278836,
                "value_ratio": 2.606432149278603
            },
            "0.375000": {
                "error_ratio": 0.7370263488946881,
                "value_ratio": 4.555972735797457
            },
            "0.425000": {
                "error_ratio": 0.7248807626845164,
                "value_ratio": 5.093833486850681
            },
            "0.475000": {
                "error_ratio": 0.7863337110575833,
                "value_ratio": 5.192400377373795
            },
            "0.525000": {
                "error_ratio": 0.38264134605323524,
                "value_ratio": 3.3230299851014
            },
            "0.575000": {
                "error_ratio": 0.3690730196886074,
                "value_ratio": 3.385785529903262
            },
            "0.625000": {
                "error_ratio": 0.22419771007605885,
                "value_ratio": 2.331327811737268
            },
            "0.675000": {
                "error_ratio": 0.2807654208042912,
                "value_ratio": 2.6149025807945034
            },
            "0.725000": {
                "error_ratio": 0.5576217562184567,
                "value_ratio": 1.6415738146272416
            }
        },
        "0.475000": {
            "0.375000": {
                "error_ratio": 0.7937044878158961,
                "value_ratio": 5.76039119971775
            },
            "0.425000": {
                "error_ratio": 0.4611886506123755,
                "value_ratio": 4.658063854241522
            },
            "0.475000": {
                "error_ratio": 0.3051388886400078,
                "value_ratio": 3.6513745544624174
            },
            "0.525000": {
                "error_ratio": 0.29403590955285436,
                "value_ratio": 3.4815837141890857
            },
            "0.575000": {
                "error_ratio": 0.19291196137680575,
                "value_ratio": 2.872099378217433
            },
            "0.625000": {
                "error_ratio": 0.22768121366067465,
                "value_ratio": 2.9489363923851193
            },
            "0.675000": {
                "error_ratio": 0.2817368813240305,
                "value_ratio": 2.1461114210714256
            }
        },
        "0.525000": {
            "0.325000": {
                "error_ratio": 1.0000199180213358,
                "value_ratio": 3.5659192617857522
            },
            "0.375000": {
                "error_ratio": 0.6120216826351008,
                "value_ratio": 4.922022777424768
            },
            "0.425000": {
                "error_ratio": 0.38872084358855524,
                "value_ratio": 4.672122947927241
            },
            "0.475000": {
                "error_ratio": 0.27461941274586427,
                "value_ratio": 3.639946703727553
            },
            "0.525000": {
                "error_ratio": 0.23462956969787918,
                "value_ratio": 3.067175010868514
            },
            "0.575000": {
                "error_ratio": 0.269853258945572,
                "value_ratio": 3.495388922333786
            },
            "0.625000": {
                "error_ratio": 0.47550196959572527,
                "value_ratio": 3.592071923920872
            }
        },
        "0.575000": {
            "0.325000": {
                "error_ratio": 1.524464161374686,
                "value_ratio": 4.226315486087734
            },
            "0.375000": {
                "error_ratio": 0.8296977235939058,
                "value_ratio": 5.589082845122238
            },
            "0.425000": {
                "error_ratio": 0.517593422336884,
                "value_ratio": 5.047225849063418
            },
            "0.475000": {
                "error_ratio": 0.3481912075774886,
                "value_ratio": 3.709515008796575
            },
            "0.525000": {
                "error_ratio": 0.43927803622141137,
                "value_ratio": 3.548636218646889
            },
            "0.575000": {
                "error_ratio": 0.8167385005523884,
                "value_ratio": 3.018114397776152
            }
        },
        "0.625000": {
            "0.375000": {
                "error_ratio": 1.028369428107695,
                "value_ratio": 4.920775604736487
            },
            "0.425000": {
                "error_ratio": 1.001475610845321,
                "value_ratio": 4.042269609257161
            },
            "0.475000": {
                "error_ratio": 1.5509127430309917,
                "value_ratio": 3.237049474522429
            }
        }
    }
}
